findjava.py
findjava-0.1.dist-info/DESCRIPTION.rst
findjava-0.1.dist-info/METADATA
findjava-0.1.dist-info/RECORD
findjava-0.1.dist-info/WHEEL
findjava-0.1.dist-info/entry_points.txt
findjava-0.1.dist-info/metadata.json
findjava-0.1.dist-info/top_level.txt
